{
  "kind": "singleType",
  "collectionName": "terms_and_conditions",
  "info": {
    "singularName": "terms-and-condition",
    "pluralName": "terms-and-conditions",
    "displayName": "Terms & Condition",
    "description": ""
  },
  "options": {
    "draftAndPublish": true
  },
  "pluginOptions": {},
  "attributes": {
    "seo": {
      "type": "component",
      "repeatable": false,
      "component": "shared.seo"
    },
    "heading": {
      "type": "string"
    },
    "image500x500": {
      "type": "media",
      "multiple": false,
      "required": false,
      "allowedTypes": [
        "images"
      ]
    },
    "content": {
      "type": "richtext"
    },
    "prefix": {
      "type": "string"
    },
    "suffix": {
      "type": "string"
    },
    "highlighted": {
      "type": "string"
    },
    "description": {
      "type": "text"
    }
  }
}
